yunxin_mcp/__init__.py
yunxin_mcp/__main__.py
yunxin_mcp/server.py
vbnmxcz_mcp_server-0.1.6.dist-info/METADATA
vbnmxcz_mcp_server-0.1.6.dist-info/WHEEL
vbnmxcz_mcp_server-0.1.6.dist-info/entry_points.txt
vbnmxcz_mcp_server-0.1.6.dist-info/licenses/LICENSE
vbnmxcz_mcp_server-0.1.6.dist-info/RECORD
