Metadata-Version: 2.4
Name: vbnmxcz-mcp-server
Version: 0.1.6
Summary: yunxin mcp server to request im/rtc api
Project-URL: Homepage, https://github.com/netease-im/yunxin-mcp-server
Author: caojiajun
Maintainer-email: caojiajun <zj_caojiajun@163.com>
License: MIT
License-File: LICENSE
Keywords: im,mcp,rtc,yunxin
Classifier: Intended Audience :: Developers
Classifier: License :: OSI Approved :: MIT License
Classifier: Programming Language :: Python :: 3
Requires-Python: >=3.11
Requires-Dist: mcp>=1.6.0
Requires-Dist: requests>=2.32.3
